neoapi/__init__.py
neoapi/client.py
neoapi/client_async.py
neoapi/client_sync.py
neoapi/config.py
neoapi/decorators.py
neoapi/exceptions.py
neoapi/models.py
neoapi/retry.py
neoapi_sdk-0.1.6.dist-info/METADATA
neoapi_sdk-0.1.6.dist-info/WHEEL
neoapi_sdk-0.1.6.dist-info/top_level.txt
neoapi_sdk-0.1.6.dist-info/RECORD
