Metadata-Version: 2.1
Name: neoapi-sdk
Version: 0.1.6
Summary: Integrate neoapi.ai LLM Analytics with your LLM pipelines.
Home-page: https://github.com/neoapi-ai/neoapi-python
Author: NeoAPI
Author-email: NeoAPI <hello@neoapi.ai>
License: Apache-2.0
Classifier: Programming Language :: Python :: 3
Classifier: License :: OSI Approved :: Apache Software License
Classifier: Operating System :: OS Independent
Requires-Python: >=3.7
Requires-Dist: aiohttp>=3.8.1
Requires-Dist: backoff>=2.2.1
Requires-Dist: pydantic>=2.0.0
Requires-Dist: asyncio>=3.4.3
Provides-Extra: dev
Requires-Dist: black>=22.3.0; extra == "dev"
Requires-Dist: isort>=5.10.1; extra == "dev"
Provides-Extra: test
Requires-Dist: pytest>=7.0.0; extra == "test"
Requires-Dist: pytest-asyncio>=0.20.0; extra == "test"
